{
  "headers": [
    {
      "tool_name": "scancode-toolkit",
      "tool_version": "3.0.2.post488.5027c75",
      "options": {},
      "notice": "Generated with ScanCode and provided on an \"AS IS\" BASIS, WITHOUT WARRANTIES\nOR CONDITIONS OF ANY KIND, either express or implied. No content created from\nScanCode should be considered or used as legal advice. Consult an Attorney\nfor any legal advice.\nScanCode is a free software code scanning tool from nexB Inc. and others.\nVisit https://github.com/nexB/scancode-toolkit/ for support and download.",
      "start_timestamp": "2019-03-31T044855.670771",
      "end_timestamp": "2019-03-31T044900.470812",
      "message": null,
      "errors": [],
      "extra_data": {
        "files_count": 20
      }
    },
    {
      "tool_name": "scancode-toolkit",
      "tool_version": "3.0.2.post488.5027c75",
      "options": {},
      "notice": "Generated with ScanCode and provided on an \"AS IS\" BASIS, WITHOUT WARRANTIES\nOR CONDITIONS OF ANY KIND, either express or implied. No content created from\nScanCode should be considered or used as legal advice. Consult an Attorney\nfor any legal advice.\nScanCode is a free software code scanning tool from nexB Inc. and others.\nVisit https://github.com/nexB/scancode-toolkit/ for support and download.",
      "start_timestamp": "2019-03-31T154205.661301",
      "end_timestamp": "2019-03-31T154205.813781",
      "message": null,
      "errors": [],
      "extra_data": {
        "files_count": 20
      }
    }
  ],
  "license_clarity_score": {
    "score": 78,
    "has_declared_license_in_key_files": true,
    "file_level_license_and_copyright_coverage": 0.13,
    "has_consistent_key_and_file_level_licenses": true,
    "is_using_only_spdx_licenses": true,
    "has_full_text_for_all_licenses": true,
    "declared": true,
    "discovered": 0.13,
    "consistency": true,
    "spdx": true,
    "license_texts": true
  },
  "files": [
    {
      "path": "gapic-google-cloud-spanner-admin-database-v1-0.15.3.tar.gz-extract",
      "type": "directory",
      "name": "gapic-google-cloud-spanner-admin-database-v1-0.15.3.tar.gz-extract",
      "base_name": "gapic-google-cloud-spanner-admin-database-v1-0.15.3.tar.gz-extract",
      "extension": "",
      "size": 0,
      "date": null,
      "sha1": null,
      "md5": null,
      "mime_type": null,
      "file_type": null,
      "programming_language": null,
      "is_binary": false,
      "is_text": false,
      "is_archive": false,
      "is_media": false,
      "is_source": false,
      "is_script": false,
      "licenses": [],
      "license_expressions": [],
      "holders": [],
      "copyrights": [],
      "authors": [],
      "packages": [],
      "is_legal": false,
      "is_manifest": false,
      "is_readme": false,
      "is_top_level": true,
      "is_key_file": false,
      "files_count": 20,
      "dirs_count": 7,
      "size_count": 56873,
      "scan_errors": []
    },
    {
      "path": "gapic-google-cloud-spanner-admin-database-v1-0.15.3.tar.gz-extract/gapic-google-cloud-spanner-admin-database-v1-0.15.3",
      "type": "directory",
      "name": "gapic-google-cloud-spanner-admin-database-v1-0.15.3",
      "base_name": "gapic-google-cloud-spanner-admin-database-v1-0.15.3",
      "extension": "",
      "size": 0,
      "date": null,
      "sha1": null,
      "md5": null,
      "mime_type": null,
      "file_type": null,
      "programming_language": null,
      "is_binary": false,
      "is_text": false,
      "is_archive": false,
      "is_media": false,
      "is_source": false,
      "is_script": false,
      "licenses": [],
      "license_expressions": [],
      "holders": [],
      "copyrights": [],
      "authors": [],
      "packages": [],
      "is_legal": false,
      "is_manifest": false,
      "is_readme": false,
      "is_top_level": true,
      "is_key_file": false,
      "files_count": 20,
      "dirs_count": 6,
      "size_count": 56873,
      "scan_errors": []
    },
    {
      "path": "gapic-google-cloud-spanner-admin-database-v1-0.15.3.tar.gz-extract/gapic-google-cloud-spanner-admin-database-v1-0.15.3/LICENSE",
      "type": "file",
      "name": "LICENSE",
      "base_name": "LICENSE",
      "extension": "",
      "size": 11352,
      "date": "2017-03-03",
      "sha1": "f305410c1669fd56efd98e0571070fad8636afcc",
      "md5": "2deedbf0e737771f60166811e74a6a92",
      "mime_type": "text/plain",
      "file_type": "ASCII text",
      "programming_language": null,
      "is_binary": false,
      "is_text": true,
      "is_archive": false,
      "is_media": false,
      "is_source": false,
      "is_script": false,
      "licenses": [
        {
          "key": "apache-2.0",
          "score": 100.0,
          "name": "Apache License 2.0",
          "short_name": "Apache 2.0",
          "category": "Permissive",
          "is_exception": false,
          "owner": "Apache Software Foundation",
          "homepage_url": "http://www.apache.org/licenses/",
          "text_url": "http://www.apache.org/licenses/LICENSE-2.0",
          "reference_url": "https://enterprise.dejacode.com/urn/urn:dje:license:apache-2.0",
          "spdx_license_key": "Apache-2.0",
          "spdx_url": "https://spdx.org/licenses/Apache-2.0",
          "start_line": 1,
          "end_line": 201,
          "matched_rule": {
            "identifier": "apache-2.0.LICENSE",
            "license_expression": "apache-2.0",
            "licenses": [
              "apache-2.0"
            ],
            "is_license_text": true,
            "is_license_notice": false,
            "is_license_reference": false,
            "is_license_tag": false,
            "matcher": "1-hash",
            "rule_length": 1582,
            "matched_length": 1582,
            "match_coverage": 100.0,
            "rule_relevance": 100
          }
        }
      ],
      "license_expressions": [
        "apache-2.0"
      ],
      "holders": [],
      "copyrights": [],
      "authors": [],
      "packages": [],
      "is_legal": true,
      "is_manifest": false,
      "is_readme": false,
      "is_top_level": true,
      "is_key_file": true,
      "files_count": 0,
      "dirs_count": 0,
      "size_count": 0,
      "scan_errors": []
    },
    {
      "path": "gapic-google-cloud-spanner-admin-database-v1-0.15.3.tar.gz-extract/gapic-google-cloud-spanner-admin-database-v1-0.15.3/MANIFEST.in",
      "type": "file",
      "name": "MANIFEST.in",
      "base_name": "MANIFEST",
      "extension": ".in",
      "size": 124,
      "date": "2017-03-03",
      "sha1": "18ff5157892ff5b341a0acaf3de6d00ec79a5869",
      "md5": "052d365ca7284f181092a815c521f0b4",
      "mime_type": "text/plain",
      "file_type": "ASCII text",
      "programming_language": null,
      "is_binary": false,
      "is_text": true,
      "is_archive": false,
      "is_media": false,
      "is_source": false,
      "is_script": false,
      "licenses": [],
      "license_expressions": [],
      "holders": [],
      "copyrights": [],
      "authors": [],
      "packages": [],
      "is_legal": false,
      "is_manifest": false,
      "is_readme": false,
      "is_top_level": true,
      "is_key_file": false,
      "files_count": 0,
      "dirs_count": 0,
      "size_count": 0,
      "scan_errors": []
    },
    {
      "path": "gapic-google-cloud-spanner-admin-database-v1-0.15.3.tar.gz-extract/gapic-google-cloud-spanner-admin-database-v1-0.15.3/PKG-INFO",
      "type": "file",
      "name": "PKG-INFO",
      "base_name": "PKG-INFO",
      "extension": "",
      "size": 3948,
      "date": "2017-03-06",
      "sha1": "8cc5c089118cfb41f348a69f49afd8ec1953cb5e",
      "md5": "d59a0c7e1b5fb4757956668edf119d6c",
      "mime_type": "text/plain",
      "file_type": "ASCII text",
      "programming_language": null,
      "is_binary": false,
      "is_text": true,
      "is_archive": false,
      "is_media": false,
      "is_source": false,
      "is_script": false,
      "licenses": [
        {
          "key": "apache-2.0",
          "score": 90.0,
          "name": "Apache License 2.0",
          "short_name": "Apache 2.0",
          "category": "Permissive",
          "is_exception": false,
          "owner": "Apache Software Foundation",
          "homepage_url": "http://www.apache.org/licenses/",
          "text_url": "http://www.apache.org/licenses/LICENSE-2.0",
          "reference_url": "https://enterprise.dejacode.com/urn/urn:dje:license:apache-2.0",
          "spdx_license_key": "Apache-2.0",
          "spdx_url": "https://spdx.org/licenses/Apache-2.0",
          "start_line": 8,
          "end_line": 8,
          "matched_rule": {
            "identifier": "apache-2.0_65.RULE",
            "license_expression": "apache-2.0",
            "licenses": [
              "apache-2.0"
            ],
            "is_license_text": false,
            "is_license_notice": false,
            "is_license_reference": false,
            "is_license_tag": true,
            "matcher": "2-aho",
            "rule_length": 4,
            "matched_length": 4,
            "match_coverage": 100.0,
            "rule_relevance": 90.0
          }
        },
        {
          "key": "apache-2.0",
          "score": 33.0,
          "name": "Apache License 2.0",
          "short_name": "Apache 2.0",
          "category": "Permissive",
          "is_exception": false,
          "owner": "Apache Software Foundation",
          "homepage_url": "http://www.apache.org/licenses/",
          "text_url": "http://www.apache.org/licenses/LICENSE-2.0",
          "reference_url": "https://enterprise.dejacode.com/urn/urn:dje:license:apache-2.0",
          "spdx_license_key": "Apache-2.0",
          "spdx_url": "https://spdx.org/licenses/Apache-2.0",
          "start_line": 92,
          "end_line": 92,
          "matched_rule": {
            "identifier": "pypi_apache_software_license.RULE",
            "license_expression": "apache-2.0",
            "licenses": [
              "apache-2.0"
            ],
            "is_license_text": false,
            "is_license_notice": false,
            "is_license_reference": false,
            "is_license_tag": true,
            "matcher": "2-aho",
            "rule_length": 6,
            "matched_length": 6,
            "match_coverage": 100.0,
            "rule_relevance": 33
          }
        }
      ],
      "license_expressions": [
        "apache-2.0",
        "apache-2.0"
      ],
      "holders": [],
      "copyrights": [],
      "authors": [
        {
          "value": "Google Inc",
          "start_line": 6,
          "end_line": 9
        }
      ],
      "packages": [],
      "is_legal": false,
      "is_manifest": false,
      "is_readme": false,
      "is_top_level": true,
      "is_key_file": false,
      "files_count": 0,
      "dirs_count": 0,
      "size_count": 0,
      "scan_errors": []
    },
    {
      "path": "gapic-google-cloud-spanner-admin-database-v1-0.15.3.tar.gz-extract/gapic-google-cloud-spanner-admin-database-v1-0.15.3/README.rst",
      "type": "file",
      "name": "README.rst",
      "base_name": "README",
      "extension": ".rst",
      "size": 2447,
      "date": "2017-03-03",
      "sha1": "691a6640c1caa3af3dfe12a06d84b790490ffa51",
      "md5": "5aeeb87862d37b9ba8b02f52075cec7a",
      "mime_type": "text/plain",
      "file_type": "ASCII text",
      "programming_language": null,
      "is_binary": false,
      "is_text": true,
      "is_archive": false,
      "is_media": false,
      "is_source": false,
      "is_script": false,
      "licenses": [],
      "license_expressions": [],
      "holders": [],
      "copyrights": [],
      "authors": [],
      "packages": [],
      "is_legal": false,
      "is_manifest": false,
      "is_readme": true,
      "is_top_level": true,
      "is_key_file": true,
      "files_count": 0,
      "dirs_count": 0,
      "size_count": 0,
      "scan_errors": []
    },
    {
      "path": "gapic-google-cloud-spanner-admin-database-v1-0.15.3.tar.gz-extract/gapic-google-cloud-spanner-admin-database-v1-0.15.3/setup.cfg",
      "type": "file",
      "name": "setup.cfg",
      "base_name": "setup",
      "extension": ".cfg",
      "size": 38,
      "date": "2017-03-06",
      "sha1": "fbb1975fd414af07da5ba9054cef698ea3b9dd4e",
      "md5": "3f78c6150b7d619a476c799812e31d5a",
      "mime_type": "text/plain",
      "file_type": "ASCII text",
      "programming_language": null,
      "is_binary": false,
      "is_text": true,
      "is_archive": false,
      "is_media": false,
      "is_source": false,
      "is_script": false,
      "licenses": [],
      "license_expressions": [],
      "holders": [],
      "copyrights": [],
      "authors": [],
      "packages": [],
      "is_legal": false,
      "is_manifest": true,
      "is_readme": false,
      "is_top_level": true,
      "is_key_file": true,
      "files_count": 0,
      "dirs_count": 0,
      "size_count": 0,
      "scan_errors": []
    },
    {
      "path": "gapic-google-cloud-spanner-admin-database-v1-0.15.3.tar.gz-extract/gapic-google-cloud-spanner-admin-database-v1-0.15.3/setup.py",
      "type": "file",
      "name": "setup.py",
      "base_name": "setup",
      "extension": ".py",
      "size": 1678,
      "date": "2017-03-06",
      "sha1": "38f8e748386ab7d2da0b29c7957df3076697c435",
      "md5": "bf33d59d28d0d8b5be92253444c5f987",
      "mime_type": "text/plain",
      "file_type": "Python script, ASCII text executable",
      "programming_language": "Python",
      "is_binary": false,
      "is_text": true,
      "is_archive": false,
      "is_media": false,
      "is_source": true,
      "is_script": true,
      "licenses": [
        {
          "key": "apache-2.0",
          "score": 33.0,
          "name": "Apache License 2.0",
          "short_name": "Apache 2.0",
          "category": "Permissive",
          "is_exception": false,
          "owner": "Apache Software Foundation",
          "homepage_url": "http://www.apache.org/licenses/",
          "text_url": "http://www.apache.org/licenses/LICENSE-2.0",
          "reference_url": "https://enterprise.dejacode.com/urn/urn:dje:license:apache-2.0",
          "spdx_license_key": "Apache-2.0",
          "spdx_url": "https://spdx.org/licenses/Apache-2.0",
          "start_line": 28,
          "end_line": 28,
          "matched_rule": {
            "identifier": "pypi_apache_software_license.RULE",
            "license_expression": "apache-2.0",
            "licenses": [
              "apache-2.0"
            ],
            "is_license_text": false,
            "is_license_notice": false,
            "is_license_reference": false,
            "is_license_tag": true,
            "matcher": "2-aho",
            "rule_length": 6,
            "matched_length": 6,
            "match_coverage": 100.0,
            "rule_relevance": 33
          }
        },
        {
          "key": "apache-2.0",
          "score": 90.0,
          "name": "Apache License 2.0",
          "short_name": "Apache 2.0",
          "category": "Permissive",
          "is_exception": false,
          "owner": "Apache Software Foundation",
          "homepage_url": "http://www.apache.org/licenses/",
          "text_url": "http://www.apache.org/licenses/LICENSE-2.0",
          "reference_url": "https://enterprise.dejacode.com/urn/urn:dje:license:apache-2.0",
          "spdx_license_key": "Apache-2.0",
          "spdx_url": "https://spdx.org/licenses/Apache-2.0",
          "start_line": 41,
          "end_line": 41,
          "matched_rule": {
            "identifier": "apache-2.0_65.RULE",
            "license_expression": "apache-2.0",
            "licenses": [
              "apache-2.0"
            ],
            "is_license_text": false,
            "is_license_notice": false,
            "is_license_reference": false,
            "is_license_tag": true,
            "matcher": "2-aho",
            "rule_length": 4,
            "matched_length": 4,
            "match_coverage": 100.0,
            "rule_relevance": 90.0
          }
        }
      ],
      "license_expressions": [
        "apache-2.0",
        "apache-2.0"
      ],
      "holders": [],
      "copyrights": [],
      "authors": [],
      "packages": [],
      "is_legal": false,
      "is_manifest": true,
      "is_readme": false,
      "is_top_level": true,
      "is_key_file": true,
      "files_count": 0,
      "dirs_count": 0,
      "size_count": 0,
      "scan_errors": []
    },
    {
      "path": "gapic-google-cloud-spanner-admin-database-v1-0.15.3.tar.gz-extract/gapic-google-cloud-spanner-admin-database-v1-0.15.3/gapic_google_cloud_spanner_admin_database_v1.egg-info",
      "type": "directory",
      "name": "gapic_google_cloud_spanner_admin_database_v1.egg-info",
      "base_name": "gapic_google_cloud_spanner_admin_database_v1.egg-info",
      "extension": "",
      "size": 0,
      "date": null,
      "sha1": null,
      "md5": null,
      "mime_type": null,
      "file_type": null,
      "programming_language": null,
      "is_binary": false,
      "is_text": false,
      "is_archive": false,
      "is_media": false,
      "is_source": false,
      "is_script": false,
      "licenses": [],
      "license_expressions": [],
      "holders": [],
      "copyrights": [],
      "authors": [],
      "packages": [],
      "is_legal": false,
      "is_manifest": false,
      "is_readme": false,
      "is_top_level": true,
      "is_key_file": false,
      "files_count": 6,
      "dirs_count": 0,
      "size_count": 5092,
      "scan_errors": []
    },
    {
      "path": "gapic-google-cloud-spanner-admin-database-v1-0.15.3.tar.gz-extract/gapic-google-cloud-spanner-admin-database-v1-0.15.3/gapic_google_cloud_spanner_admin_database_v1.egg-info/dependency_links.txt",
      "type": "file",
      "name": "dependency_links.txt",
      "base_name": "dependency_links",
      "extension": ".txt",
      "size": 1,
      "date": "2017-03-06",
      "sha1": "adc83b19e793491b1c6ea0fd8b46cd9f32e592fc",
      "md5": "68b329da9893e34099c7d8ad5cb9c940",
      "mime_type": "application/octet-stream",
      "file_type": "very short file (no magic)",
      "programming_language": null,
      "is_binary": false,
      "is_text": true,
      "is_archive": false,
      "is_media": false,
      "is_source": false,
      "is_script": false,
      "licenses": [],
      "license_expressions": [],
      "holders": [],
      "copyrights": [],
      "authors": [],
      "packages": [],
      "is_legal": false,
      "is_manifest": false,
      "is_readme": false,
      "is_top_level": false,
      "is_key_file": false,
      "files_count": 0,
      "dirs_count": 0,
      "size_count": 0,
      "scan_errors": []
    },
    {
      "path": "gapic-google-cloud-spanner-admin-database-v1-0.15.3.tar.gz-extract/gapic-google-cloud-spanner-admin-database-v1-0.15.3/gapic_google_cloud_spanner_admin_database_v1.egg-info/namespace_packages.txt",
      "type": "file",
      "name": "namespace_packages.txt",
      "base_name": "namespace_packages",
      "extension": ".txt",
      "size": 81,
      "date": "2017-03-06",
      "sha1": "ac0712aab1b7166441b6f735425447885b822e15",
      "md5": "a726ab122d25b5bf1bd6ad6fb00416b2",
      "mime_type": "text/plain",
      "file_type": "ASCII text",
      "programming_language": null,
      "is_binary": false,
      "is_text": true,
      "is_archive": false,
      "is_media": false,
      "is_source": false,
      "is_script": false,
      "licenses": [],
      "license_expressions": [],
      "holders": [],
      "copyrights": [],
      "authors": [],
      "packages": [],
      "is_legal": false,
      "is_manifest": false,
      "is_readme": false,
      "is_top_level": false,
      "is_key_file": false,
      "files_count": 0,
      "dirs_count": 0,
      "size_count": 0,
      "scan_errors": []
    },
    {
      "path": "gapic-google-cloud-spanner-admin-database-v1-0.15.3.tar.gz-extract/gapic-google-cloud-spanner-admin-database-v1-0.15.3/gapic_google_cloud_spanner_admin_database_v1.egg-info/PKG-INFO",
      "type": "file",
      "name": "PKG-INFO",
      "base_name": "PKG-INFO",
      "extension": "",
      "size": 3948,
      "date": "2017-03-06",
      "sha1": "8cc5c089118cfb41f348a69f49afd8ec1953cb5e",
      "md5": "d59a0c7e1b5fb4757956668edf119d6c",
      "mime_type": "text/plain",
      "file_type": "ASCII text",
      "programming_language": null,
      "is_binary": false,
      "is_text": true,
      "is_archive": false,
      "is_media": false,
      "is_source": false,
      "is_script": false,
      "licenses": [
        {
          "key": "apache-2.0",
          "score": 90.0,
          "name": "Apache License 2.0",
          "short_name": "Apache 2.0",
          "category": "Permissive",
          "is_exception": false,
          "owner": "Apache Software Foundation",
          "homepage_url": "http://www.apache.org/licenses/",
          "text_url": "http://www.apache.org/licenses/LICENSE-2.0",
          "reference_url": "https://enterprise.dejacode.com/urn/urn:dje:license:apache-2.0",
          "spdx_license_key": "Apache-2.0",
          "spdx_url": "https://spdx.org/licenses/Apache-2.0",
          "start_line": 8,
          "end_line": 8,
          "matched_rule": {
            "identifier": "apache-2.0_65.RULE",
            "license_expression": "apache-2.0",
            "licenses": [
              "apache-2.0"
            ],
            "is_license_text": false,
            "is_license_notice": false,
            "is_license_reference": false,
            "is_license_tag": true,
            "matcher": "2-aho",
            "rule_length": 4,
            "matched_length": 4,
            "match_coverage": 100.0,
            "rule_relevance": 90.0
          }
        },
        {
          "key": "apache-2.0",
          "score": 33.0,
          "name": "Apache License 2.0",
          "short_name": "Apache 2.0",
          "category": "Permissive",
          "is_exception": false,
          "owner": "Apache Software Foundation",
          "homepage_url": "http://www.apache.org/licenses/",
          "text_url": "http://www.apache.org/licenses/LICENSE-2.0",
          "reference_url": "https://enterprise.dejacode.com/urn/urn:dje:license:apache-2.0",
          "spdx_license_key": "Apache-2.0",
          "spdx_url": "https://spdx.org/licenses/Apache-2.0",
          "start_line": 92,
          "end_line": 92,
          "matched_rule": {
            "identifier": "pypi_apache_software_license.RULE",
            "license_expression": "apache-2.0",
            "licenses": [
              "apache-2.0"
            ],
            "is_license_text": false,
            "is_license_notice": false,
            "is_license_reference": false,
            "is_license_tag": true,
            "matcher": "2-aho",
            "rule_length": 6,
            "matched_length": 6,
            "match_coverage": 100.0,
            "rule_relevance": 33
          }
        }
      ],
      "license_expressions": [
        "apache-2.0",
        "apache-2.0"
      ],
      "holders": [],
      "copyrights": [],
      "authors": [
        {
          "value": "Google Inc",
          "start_line": 6,
          "end_line": 9
        }
      ],
      "packages": [],
      "is_legal": false,
      "is_manifest": false,
      "is_readme": false,
      "is_top_level": false,
      "is_key_file": false,
      "files_count": 0,
      "dirs_count": 0,
      "size_count": 0,
      "scan_errors": []
    },
    {
      "path": "gapic-google-cloud-spanner-admin-database-v1-0.15.3.tar.gz-extract/gapic-google-cloud-spanner-admin-database-v1-0.15.3/gapic_google_cloud_spanner_admin_database_v1.egg-info/requires.txt",
      "type": "file",
      "name": "requires.txt",
      "base_name": "requires",
      "extension": ".txt",
      "size": 211,
      "date": "2017-03-06",
      "sha1": "2ec27c3d8fdf35961c47754550dcd2762dfc2d00",
      "md5": "0ad3eb0b2ce12b0fc012af90c3e86c8c",
      "mime_type": "text/plain",
      "file_type": "ASCII text",
      "programming_language": null,
      "is_binary": false,
      "is_text": true,
      "is_archive": false,
      "is_media": false,
      "is_source": false,
      "is_script": false,
      "licenses": [],
      "license_expressions": [],
      "holders": [],
      "copyrights": [],
      "authors": [],
      "packages": [],
      "is_legal": false,
      "is_manifest": false,
      "is_readme": false,
      "is_top_level": false,
      "is_key_file": false,
      "files_count": 0,
      "dirs_count": 0,
      "size_count": 0,
      "scan_errors": []
    },
    {
      "path": "gapic-google-cloud-spanner-admin-database-v1-0.15.3.tar.gz-extract/gapic-google-cloud-spanner-admin-database-v1-0.15.3/gapic_google_cloud_spanner_admin_database_v1.egg-info/SOURCES.txt",
      "type": "file",
      "name": "SOURCES.txt",
      "base_name": "SOURCES",
      "extension": ".txt",
      "size": 844,
      "date": "2017-03-06",
      "sha1": "361e9363caaf4c162e0fb298004b3cb8e0d448e6",
      "md5": "a0975cb99d8e2506dbbad32d7945e7ee",
      "mime_type": "text/plain",
      "file_type": "ASCII text",
      "programming_language": null,
      "is_binary": false,
      "is_text": true,
      "is_archive": false,
      "is_media": false,
      "is_source": false,
      "is_script": false,
      "licenses": [],
      "license_expressions": [],
      "holders": [],
      "copyrights": [],
      "authors": [],
      "packages": [],
      "is_legal": false,
      "is_manifest": false,
      "is_readme": false,
      "is_top_level": false,
      "is_key_file": false,
      "files_count": 0,
      "dirs_count": 0,
      "size_count": 0,
      "scan_errors": []
    },
    {
      "path": "gapic-google-cloud-spanner-admin-database-v1-0.15.3.tar.gz-extract/gapic-google-cloud-spanner-admin-database-v1-0.15.3/gapic_google_cloud_spanner_admin_database_v1.egg-info/top_level.txt",
      "type": "file",
      "name": "top_level.txt",
      "base_name": "top_level",
      "extension": ".txt",
      "size": 7,
      "date": "2017-03-06",
      "sha1": "d662cc72cfed7244a88a7360add85d5627b9cd6c",
      "md5": "0cfa9f600839f57e90e5559b8ee54864",
      "mime_type": "text/plain",
      "file_type": "ASCII text",
      "programming_language": null,
      "is_binary": false,
      "is_text": true,
      "is_archive": false,
      "is_media": false,
      "is_source": false,
      "is_script": false,
      "licenses": [],
      "license_expressions": [],
      "holders": [],
      "copyrights": [],
      "authors": [],
      "packages": [],
      "is_legal": false,
      "is_manifest": false,
      "is_readme": false,
      "is_top_level": false,
      "is_key_file": false,
      "files_count": 0,
      "dirs_count": 0,
      "size_count": 0,
      "scan_errors": []
    },
    {
      "path": "gapic-google-cloud-spanner-admin-database-v1-0.15.3.tar.gz-extract/gapic-google-cloud-spanner-admin-database-v1-0.15.3/google",
      "type": "directory",
      "name": "google",
      "base_name": "google",
      "extension": "",
      "size": 0,
      "date": null,
      "sha1": null,
      "md5": null,
      "mime_type": null,
      "file_type": null,
      "programming_language": null,
      "is_binary": false,
      "is_text": false,
      "is_archive": false,
      "is_media": false,
      "is_source": false,
      "is_script": false,
      "licenses": [],
      "license_expressions": [],
      "holders": [],
      "copyrights": [],
      "authors": [],
      "packages": [],
      "is_legal": false,
      "is_manifest": false,
      "is_readme": false,
      "is_top_level": true,
      "is_key_file": false,
      "files_count": 8,
      "dirs_count": 4,
      "size_count": 32194,
      "scan_errors": []
    },
    {
      "path": "gapic-google-cloud-spanner-admin-database-v1-0.15.3.tar.gz-extract/gapic-google-cloud-spanner-admin-database-v1-0.15.3/google/__init__.py",
      "type": "file",
      "name": "__init__.py",
      "base_name": "__init__",
      "extension": ".py",
      "size": 56,
      "date": "2017-03-03",
      "sha1": "c782af2d3d8a2b84f982b211d971115434985b12",
      "md5": "050042c7144e01b0a29eb3d46929e962",
      "mime_type": "text/plain",
      "file_type": "ASCII text",
      "programming_language": "Python",
      "is_binary": false,
      "is_text": true,
      "is_archive": false,
      "is_media": false,
      "is_source": true,
      "is_script": false,
      "licenses": [],
      "license_expressions": [],
      "holders": [],
      "copyrights": [],
      "authors": [],
      "packages": [],
      "is_legal": false,
      "is_manifest": false,
      "is_readme": false,
      "is_top_level": false,
      "is_key_file": false,
      "files_count": 0,
      "dirs_count": 0,
      "size_count": 0,
      "scan_errors": []
    },
    {
      "path": "gapic-google-cloud-spanner-admin-database-v1-0.15.3.tar.gz-extract/gapic-google-cloud-spanner-admin-database-v1-0.15.3/google/cloud",
      "type": "directory",
      "name": "cloud",
      "base_name": "cloud",
      "extension": "",
      "size": 0,
      "date": null,
      "sha1": null,
      "md5": null,
      "mime_type": null,
      "file_type": null,
      "programming_language": null,
      "is_binary": false,
      "is_text": false,
      "is_archive": false,
      "is_media": false,
      "is_source": false,
      "is_script": false,
      "licenses": [],
      "license_expressions": [],
      "holders": [],
      "copyrights": [],
      "authors": [],
      "packages": [],
      "is_legal": false,
      "is_manifest": false,
      "is_readme": false,
      "is_top_level": false,
      "is_key_file": false,
      "files_count": 7,
      "dirs_count": 3,
      "size_count": 32138,
      "scan_errors": []
    },
    {
      "path": "gapic-google-cloud-spanner-admin-database-v1-0.15.3.tar.gz-extract/gapic-google-cloud-spanner-admin-database-v1-0.15.3/google/cloud/__init__.py",
      "type": "file",
      "name": "__init__.py",
      "base_name": "__init__",
      "extension": ".py",
      "size": 56,
      "date": "2017-03-03",
      "sha1": "c782af2d3d8a2b84f982b211d971115434985b12",
      "md5": "050042c7144e01b0a29eb3d46929e962",
      "mime_type": "text/plain",
      "file_type": "ASCII text",
      "programming_language": "Python",
      "is_binary": false,
      "is_text": true,
      "is_archive": false,
      "is_media": false,
      "is_source": true,
      "is_script": false,
      "licenses": [],
      "license_expressions": [],
      "holders": [],
      "copyrights": [],
      "authors": [],
      "packages": [],
      "is_legal": false,
      "is_manifest": false,
      "is_readme": false,
      "is_top_level": false,
      "is_key_file": false,
      "files_count": 0,
      "dirs_count": 0,
      "size_count": 0,
      "scan_errors": []
    },
    {
      "path": "gapic-google-cloud-spanner-admin-database-v1-0.15.3.tar.gz-extract/gapic-google-cloud-spanner-admin-database-v1-0.15.3/google/cloud/gapic",
      "type": "directory",
      "name": "gapic",
      "base_name": "gapic",
      "extension": "",
      "size": 0,
      "date": null,
      "sha1": null,
      "md5": null,
      "mime_type": null,
      "file_type": null,
      "programming_language": null,
      "is_binary": false,
      "is_text": false,
      "is_archive": false,
      "is_media": false,
      "is_source": false,
      "is_script": false,
      "licenses": [],
      "license_expressions": [],
      "holders": [],
      "copyrights": [],
      "authors": [],
      "packages": [],
      "is_legal": false,
      "is_manifest": false,
      "is_readme": false,
      "is_top_level": false,
      "is_key_file": false,
      "files_count": 6,
      "dirs_count": 2,
      "size_count": 32082,
      "scan_errors": []
    },
    {
      "path": "gapic-google-cloud-spanner-admin-database-v1-0.15.3.tar.gz-extract/gapic-google-cloud-spanner-admin-database-v1-0.15.3/google/cloud/gapic/__init__.py",
      "type": "file",
      "name": "__init__.py",
      "base_name": "__init__",
      "extension": ".py",
      "size": 56,
      "date": "2017-03-03",
      "sha1": "c782af2d3d8a2b84f982b211d971115434985b12",
      "md5": "050042c7144e01b0a29eb3d46929e962",
      "mime_type": "text/plain",
      "file_type": "ASCII text",
      "programming_language": "Python",
      "is_binary": false,
      "is_text": true,
      "is_archive": false,
      "is_media": false,
      "is_source": true,
      "is_script": false,
      "licenses": [],
      "license_expressions": [],
      "holders": [],
      "copyrights": [],
      "authors": [],
      "packages": [],
      "is_legal": false,
      "is_manifest": false,
      "is_readme": false,
      "is_top_level": false,
      "is_key_file": false,
      "files_count": 0,
      "dirs_count": 0,
      "size_count": 0,
      "scan_errors": []
    },
    {
      "path": "gapic-google-cloud-spanner-admin-database-v1-0.15.3.tar.gz-extract/gapic-google-cloud-spanner-admin-database-v1-0.15.3/google/cloud/gapic/spanner_admin_database",
      "type": "directory",
      "name": "spanner_admin_database",
      "base_name": "spanner_admin_database",
      "extension": "",
      "size": 0,
      "date": null,
      "sha1": null,
      "md5": null,
      "mime_type": null,
      "file_type": null,
      "programming_language": null,
      "is_binary": false,
      "is_text": false,
      "is_archive": false,
      "is_media": false,
      "is_source": false,
      "is_script": false,
      "licenses": [],
      "license_expressions": [],
      "holders": [],
      "copyrights": [],
      "authors": [],
      "packages": [],
      "is_legal": false,
      "is_manifest": false,
      "is_readme": false,
      "is_top_level": false,
      "is_key_file": false,
      "files_count": 5,
      "dirs_count": 1,
      "size_count": 32026,
      "scan_errors": []
    },
    {
      "path": "gapic-google-cloud-spanner-admin-database-v1-0.15.3.tar.gz-extract/gapic-google-cloud-spanner-admin-database-v1-0.15.3/google/cloud/gapic/spanner_admin_database/__init__.py",
      "type": "file",
      "name": "__init__.py",
      "base_name": "__init__",
      "extension": ".py",
      "size": 56,
      "date": "2017-03-03",
      "sha1": "c782af2d3d8a2b84f982b211d971115434985b12",
      "md5": "050042c7144e01b0a29eb3d46929e962",
      "mime_type": "text/plain",
      "file_type": "ASCII text",
      "programming_language": "Python",
      "is_binary": false,
      "is_text": true,
      "is_archive": false,
      "is_media": false,
      "is_source": true,
      "is_script": false,
      "licenses": [],
      "license_expressions": [],
      "holders": [],
      "copyrights": [],
      "authors": [],
      "packages": [],
      "is_legal": false,
      "is_manifest": false,
      "is_readme": false,
      "is_top_level": false,
      "is_key_file": false,
      "files_count": 0,
      "dirs_count": 0,
      "size_count": 0,
      "scan_errors": []
    },
    {
      "path": "gapic-google-cloud-spanner-admin-database-v1-0.15.3.tar.gz-extract/gapic-google-cloud-spanner-admin-database-v1-0.15.3/google/cloud/gapic/spanner_admin_database/v1",
      "type": "directory",
      "name": "v1",
      "base_name": "v1",
      "extension": "",
      "size": 0,
      "date": null,
      "sha1": null,
      "md5": null,
      "mime_type": null,
      "file_type": null,
      "programming_language": null,
      "is_binary": false,
      "is_text": false,
      "is_archive": false,
      "is_media": false,
      "is_source": false,
      "is_script": false,
      "licenses": [],
      "license_expressions": [],
      "holders": [],
      "copyrights": [],
      "authors": [],
      "packages": [],
      "is_legal": false,
      "is_manifest": false,
      "is_readme": false,
      "is_top_level": false,
      "is_key_file": false,
      "files_count": 4,
      "dirs_count": 0,
      "size_count": 31970,
      "scan_errors": []
    },
    {
      "path": "gapic-google-cloud-spanner-admin-database-v1-0.15.3.tar.gz-extract/gapic-google-cloud-spanner-admin-database-v1-0.15.3/google/cloud/gapic/spanner_admin_database/v1/__init__.py",
      "type": "file",
      "name": "__init__.py",
      "base_name": "__init__",
      "extension": ".py",
      "size": 0,
      "date": "2017-03-03",
      "sha1": null,
      "md5": null,
      "mime_type": "inode/x-empty",
      "file_type": "empty",
      "programming_language": "Python",
      "is_binary": false,
      "is_text": true,
      "is_archive": false,
      "is_media": false,
      "is_source": true,
      "is_script": false,
      "licenses": [],
      "license_expressions": [],
      "holders": [],
      "copyrights": [],
      "authors": [],
      "packages": [],
      "is_legal": false,
      "is_manifest": false,
      "is_readme": false,
      "is_top_level": false,
      "is_key_file": false,
      "files_count": 0,
      "dirs_count": 0,
      "size_count": 0,
      "scan_errors": []
    },
    {
      "path": "gapic-google-cloud-spanner-admin-database-v1-0.15.3.tar.gz-extract/gapic-google-cloud-spanner-admin-database-v1-0.15.3/google/cloud/gapic/spanner_admin_database/v1/database_admin_client.py",
      "type": "file",
      "name": "database_admin_client.py",
      "base_name": "database_admin_client",
      "extension": ".py",
      "size": 28732,
      "date": "2017-03-06",
      "sha1": "37d0726efc73672c5f571a7819e29ef4534e9c6b",
      "md5": "6cc5d88efa96758b01c5b96240265c96",
      "mime_type": "text/x-python",
      "file_type": "Python script, ASCII text executable",
      "programming_language": "Python",
      "is_binary": false,
      "is_text": true,
      "is_archive": false,
      "is_media": false,
      "is_source": true,
      "is_script": true,
      "licenses": [
        {
          "key": "apache-2.0",
          "score": 100.0,
          "name": "Apache License 2.0",
          "short_name": "Apache 2.0",
          "category": "Permissive",
          "is_exception": false,
          "owner": "Apache Software Foundation",
          "homepage_url": "http://www.apache.org/licenses/",
          "text_url": "http://www.apache.org/licenses/LICENSE-2.0",
          "reference_url": "https://enterprise.dejacode.com/urn/urn:dje:license:apache-2.0",
          "spdx_license_key": "Apache-2.0",
          "spdx_url": "https://spdx.org/licenses/Apache-2.0",
          "start_line": 3,
          "end_line": 13,
          "matched_rule": {
            "identifier": "apache-2.0_7.RULE",
            "license_expression": "apache-2.0",
            "licenses": [
              "apache-2.0"
            ],
            "is_license_text": false,
            "is_license_notice": true,
            "is_license_reference": false,
            "is_license_tag": false,
            "matcher": "2-aho",
            "rule_length": 85,
            "matched_length": 85,
            "match_coverage": 100.0,
            "rule_relevance": 100
          }
        }
      ],
      "license_expressions": [
        "apache-2.0"
      ],
      "holders": [
        {
          "value": "Google Inc.",
          "start_line": 1,
          "end_line": 1
        }
      ],
      "copyrights": [
        {
          "value": "Copyright 2017, Google Inc.",
          "start_line": 1,
          "end_line": 1
        }
      ],
      "authors": [],
      "packages": [],
      "is_legal": false,
      "is_manifest": false,
      "is_readme": false,
      "is_top_level": false,
      "is_key_file": false,
      "files_count": 0,
      "dirs_count": 0,
      "size_count": 0,
      "scan_errors": []
    },
    {
      "path": "gapic-google-cloud-spanner-admin-database-v1-0.15.3.tar.gz-extract/gapic-google-cloud-spanner-admin-database-v1-0.15.3/google/cloud/gapic/spanner_admin_database/v1/database_admin_client_config.json",
      "type": "file",
      "name": "database_admin_client_config.json",
      "base_name": "database_admin_client_config",
      "extension": ".json",
      "size": 2104,
      "date": "2017-03-06",
      "sha1": "09d9cb953bbc0a82a0a51ad0bf6c4e57b974e107",
      "md5": "ef656e179d792b85e930e9dcbe9c6e20",
      "mime_type": "text/plain",
      "file_type": "ASCII text",
      "programming_language": null,
      "is_binary": false,
      "is_text": true,
      "is_archive": false,
      "is_media": false,
      "is_source": false,
      "is_script": false,
      "licenses": [],
      "license_expressions": [],
      "holders": [],
      "copyrights": [],
      "authors": [],
      "packages": [],
      "is_legal": false,
      "is_manifest": false,
      "is_readme": false,
      "is_top_level": false,
      "is_key_file": false,
      "files_count": 0,
      "dirs_count": 0,
      "size_count": 0,
      "scan_errors": []
    },
    {
      "path": "gapic-google-cloud-spanner-admin-database-v1-0.15.3.tar.gz-extract/gapic-google-cloud-spanner-admin-database-v1-0.15.3/google/cloud/gapic/spanner_admin_database/v1/enums.py",
      "type": "file",
      "name": "enums.py",
      "base_name": "enums",
      "extension": ".py",
      "size": 1134,
      "date": "2017-03-03",
      "sha1": "bef50c3da68ee121e2804203e85db7796217bb19",
      "md5": "b7280be7d2425f5b2bc7c92c0afd85b4",
      "mime_type": "text/x-c++",
      "file_type": "C++ source, ASCII text",
      "programming_language": "Python",
      "is_binary": false,
      "is_text": true,
      "is_archive": false,
      "is_media": false,
      "is_source": true,
      "is_script": false,
      "licenses": [
        {
          "key": "apache-2.0",
          "score": 100.0,
          "name": "Apache License 2.0",
          "short_name": "Apache 2.0",
          "category": "Permissive",
          "is_exception": false,
          "owner": "Apache Software Foundation",
          "homepage_url": "http://www.apache.org/licenses/",
          "text_url": "http://www.apache.org/licenses/LICENSE-2.0",
          "reference_url": "https://enterprise.dejacode.com/urn/urn:dje:license:apache-2.0",
          "spdx_license_key": "Apache-2.0",
          "spdx_url": "https://spdx.org/licenses/Apache-2.0",
          "start_line": 3,
          "end_line": 13,
          "matched_rule": {
            "identifier": "apache-2.0_7.RULE",
            "license_expression": "apache-2.0",
            "licenses": [
              "apache-2.0"
            ],
            "is_license_text": false,
            "is_license_notice": true,
            "is_license_reference": false,
            "is_license_tag": false,
            "matcher": "2-aho",
            "rule_length": 85,
            "matched_length": 85,
            "match_coverage": 100.0,
            "rule_relevance": 100
          }
        }
      ],
      "license_expressions": [
        "apache-2.0"
      ],
      "holders": [
        {
          "value": "Google Inc.",
          "start_line": 1,
          "end_line": 1
        }
      ],
      "copyrights": [
        {
          "value": "Copyright 2016 Google Inc.",
          "start_line": 1,
          "end_line": 1
        }
      ],
      "authors": [],
      "packages": [],
      "is_legal": false,
      "is_manifest": false,
      "is_readme": false,
      "is_top_level": false,
      "is_key_file": false,
      "files_count": 0,
      "dirs_count": 0,
      "size_count": 0,
      "scan_errors": []
    }
  ]
}
