{
  "headers": [
    {
      "tool_name": "scancode-toolkit",
      "tool_version": "3.0.2.post488.5027c75",
      "options": {},
      "notice": "Generated with ScanCode and provided on an \"AS IS\" BASIS, WITHOUT WARRANTIES\nOR CONDITIONS OF ANY KIND, either express or implied. No content created from\nScanCode should be considered or used as legal advice. Consult an Attorney\nfor any legal advice.\nScanCode is a free software code scanning tool from nexB Inc. and others.\nVisit https://github.com/nexB/scancode-toolkit/ for support and download.",
      "start_timestamp": "2019-03-31T040522.240430",
      "end_timestamp": "2019-03-31T040525.843534",
      "message": null,
      "errors": [],
      "extra_data": {
        "files_count": 13
      }
    },
    {
      "tool_name": "scancode-toolkit",
      "tool_version": "3.0.2.post488.5027c75",
      "options": {},
      "notice": "Generated with ScanCode and provided on an \"AS IS\" BASIS, WITHOUT WARRANTIES\nOR CONDITIONS OF ANY KIND, either express or implied. No content created from\nScanCode should be considered or used as legal advice. Consult an Attorney\nfor any legal advice.\nScanCode is a free software code scanning tool from nexB Inc. and others.\nVisit https://github.com/nexB/scancode-toolkit/ for support and download.",
      "start_timestamp": "2019-03-31T154102.191690",
      "end_timestamp": "2019-03-31T154102.282384",
      "message": null,
      "errors": [],
      "extra_data": {
        "files_count": 13
      }
    }
  ],
  "license_clarity_score": {
    "score": 45,
    "has_declared_license_in_key_files": true,
    "file_level_license_and_copyright_coverage": 0.0,
    "has_consistent_key_and_file_level_licenses": false,
    "is_using_only_spdx_licenses": true,
    "has_full_text_for_all_licenses": false,
    "declared": true,
    "discovered": 0.0,
    "consistency": false,
    "spdx": true,
    "license_texts": false
  },
  "files": [
    {
      "path": "letsencrypt-0.7.0.tar.gz-extract",
      "type": "directory",
      "name": "letsencrypt-0.7.0.tar.gz-extract",
      "base_name": "letsencrypt-0.7.0.tar.gz-extract",
      "extension": "",
      "size": 0,
      "date": null,
      "sha1": null,
      "md5": null,
      "mime_type": null,
      "file_type": null,
      "programming_language": null,
      "is_binary": false,
      "is_text": false,
      "is_archive": false,
      "is_media": false,
      "is_source": false,
      "is_script": false,
      "licenses": [],
      "license_expressions": [],
      "holders": [],
      "copyrights": [],
      "authors": [],
      "packages": [],
      "is_legal": false,
      "is_manifest": false,
      "is_readme": false,
      "is_top_level": true,
      "is_key_file": false,
      "files_count": 13,
      "dirs_count": 3,
      "size_count": 15999,
      "scan_errors": []
    },
    {
      "path": "letsencrypt-0.7.0.tar.gz-extract/letsencrypt-0.7.0",
      "type": "directory",
      "name": "letsencrypt-0.7.0",
      "base_name": "letsencrypt-0.7.0",
      "extension": "",
      "size": 0,
      "date": null,
      "sha1": null,
      "md5": null,
      "mime_type": null,
      "file_type": null,
      "programming_language": null,
      "is_binary": false,
      "is_text": false,
      "is_archive": false,
      "is_media": false,
      "is_source": false,
      "is_script": false,
      "licenses": [],
      "license_expressions": [],
      "holders": [],
      "copyrights": [],
      "authors": [],
      "packages": [],
      "is_legal": false,
      "is_manifest": false,
      "is_readme": false,
      "is_top_level": true,
      "is_key_file": false,
      "files_count": 13,
      "dirs_count": 2,
      "size_count": 15999,
      "scan_errors": []
    },
    {
      "path": "letsencrypt-0.7.0.tar.gz-extract/letsencrypt-0.7.0/LICENSE.txt",
      "type": "file",
      "name": "LICENSE.txt",
      "base_name": "LICENSE",
      "extension": ".txt",
      "size": 11462,
      "date": "2016-05-27",
      "sha1": "4057c44b3b3fb4303c847dda300b18bdd2df44b1",
      "md5": "09f03be91f858f698dd88eeacc86f131",
      "mime_type": "text/plain",
      "file_type": "ASCII text",
      "programming_language": null,
      "is_binary": false,
      "is_text": true,
      "is_archive": false,
      "is_media": false,
      "is_source": false,
      "is_script": false,
      "licenses": [
        {
          "key": "mit",
          "score": 80.0,
          "name": "MIT License",
          "short_name": "MIT License",
          "category": "Permissive",
          "is_exception": false,
          "owner": "MIT",
          "homepage_url": "http://opensource.org/licenses/mit-license.php",
          "text_url": "http://opensource.org/licenses/mit-license.php",
          "reference_url": "https://enterprise.dejacode.com/urn/urn:dje:license:mit",
          "spdx_license_key": "MIT",
          "spdx_url": "https://spdx.org/licenses/MIT",
          "start_line": 7,
          "end_line": 7,
          "matched_rule": {
            "identifier": "mit_48.RULE",
            "license_expression": "mit",
            "licenses": [
              "mit"
            ],
            "is_license_text": false,
            "is_license_notice": false,
            "is_license_reference": true,
            "is_license_tag": false,
            "matcher": "2-aho",
            "rule_length": 2,
            "matched_length": 2,
            "match_coverage": 100.0,
            "rule_relevance": 80.0
          }
        },
        {
          "key": "apache-2.0",
          "score": 100.0,
          "name": "Apache License 2.0",
          "short_name": "Apache 2.0",
          "category": "Permissive",
          "is_exception": false,
          "owner": "Apache Software Foundation",
          "homepage_url": "http://www.apache.org/licenses/",
          "text_url": "http://www.apache.org/licenses/LICENSE-2.0",
          "reference_url": "https://enterprise.dejacode.com/urn/urn:dje:license:apache-2.0",
          "spdx_license_key": "Apache-2.0",
          "spdx_url": "https://spdx.org/licenses/Apache-2.0",
          "start_line": 12,
          "end_line": 185,
          "matched_rule": {
            "identifier": "apache-2.0_93.RULE",
            "license_expression": "apache-2.0",
            "licenses": [
              "apache-2.0"
            ],
            "is_license_text": false,
            "is_license_notice": true,
            "is_license_reference": false,
            "is_license_tag": false,
            "matcher": "2-aho",
            "rule_length": 1403,
            "matched_length": 1403,
            "match_coverage": 100.0,
            "rule_relevance": 100
          }
        },
        {
          "key": "mit",
          "score": 100.0,
          "name": "MIT License",
          "short_name": "MIT License",
          "category": "Permissive",
          "is_exception": false,
          "owner": "MIT",
          "homepage_url": "http://opensource.org/licenses/mit-license.php",
          "text_url": "http://opensource.org/licenses/mit-license.php",
          "reference_url": "https://enterprise.dejacode.com/urn/urn:dje:license:mit",
          "spdx_license_key": "MIT",
          "spdx_url": "https://spdx.org/licenses/MIT",
          "start_line": 188,
          "end_line": 205,
          "matched_rule": {
            "identifier": "mit_41.RULE",
            "license_expression": "mit",
            "licenses": [
              "mit"
            ],
            "is_license_text": true,
            "is_license_notice": false,
            "is_license_reference": false,
            "is_license_tag": false,
            "matcher": "2-aho",
            "rule_length": 163,
            "matched_length": 163,
            "match_coverage": 100.0,
            "rule_relevance": 100
          }
        }
      ],
      "license_expressions": [
        "mit",
        "apache-2.0",
        "mit"
      ],
      "holders": [
        {
          "value": "Electronic Frontier Foundation and others",
          "start_line": 2,
          "end_line": 3
        },
        {
          "value": "Fatih Erikli",
          "start_line": 6,
          "end_line": 7
        }
      ],
      "copyrights": [
        {
          "value": "Copyright (c) Electronic Frontier Foundation and others",
          "start_line": 2,
          "end_line": 3
        },
        {
          "value": "Copyright (c) 2014 Fatih Erikli",
          "start_line": 6,
          "end_line": 7
        }
      ],
      "authors": [],
      "packages": [],
      "is_legal": true,
      "is_manifest": false,
      "is_readme": false,
      "is_top_level": true,
      "is_key_file": true,
      "files_count": 0,
      "dirs_count": 0,
      "size_count": 0,
      "scan_errors": []
    },
    {
      "path": "letsencrypt-0.7.0.tar.gz-extract/letsencrypt-0.7.0/MANIFEST.in",
      "type": "file",
      "name": "MANIFEST.in",
      "base_name": "MANIFEST",
      "extension": ".in",
      "size": 39,
      "date": "2016-05-27",
      "sha1": "4967b8cefc6237eb0bc479857473dfe67010287a",
      "md5": "ca3e4f2c7de630575d85707e9092777b",
      "mime_type": "text/plain",
      "file_type": "ASCII text",
      "programming_language": null,
      "is_binary": false,
      "is_text": true,
      "is_archive": false,
      "is_media": false,
      "is_source": false,
      "is_script": false,
      "licenses": [],
      "license_expressions": [],
      "holders": [],
      "copyrights": [],
      "authors": [],
      "packages": [],
      "is_legal": false,
      "is_manifest": false,
      "is_readme": false,
      "is_top_level": true,
      "is_key_file": false,
      "files_count": 0,
      "dirs_count": 0,
      "size_count": 0,
      "scan_errors": []
    },
    {
      "path": "letsencrypt-0.7.0.tar.gz-extract/letsencrypt-0.7.0/PKG-INFO",
      "type": "file",
      "name": "PKG-INFO",
      "base_name": "PKG-INFO",
      "extension": "",
      "size": 1094,
      "date": "2016-05-27",
      "sha1": "049a7926c19876243bde3438eaf872bce00688ea",
      "md5": "ab37a1b85527b8bd13188b6363133db3",
      "mime_type": "text/plain",
      "file_type": "ASCII text",
      "programming_language": null,
      "is_binary": false,
      "is_text": true,
      "is_archive": false,
      "is_media": false,
      "is_source": false,
      "is_script": false,
      "licenses": [
        {
          "key": "apache-2.0",
          "score": 27.0,
          "name": "Apache License 2.0",
          "short_name": "Apache 2.0",
          "category": "Permissive",
          "is_exception": false,
          "owner": "Apache Software Foundation",
          "homepage_url": "http://www.apache.org/licenses/",
          "text_url": "http://www.apache.org/licenses/LICENSE-2.0",
          "reference_url": "https://enterprise.dejacode.com/urn/urn:dje:license:apache-2.0",
          "spdx_license_key": "Apache-2.0",
          "spdx_url": "https://spdx.org/licenses/Apache-2.0",
          "start_line": 8,
          "end_line": 8,
          "matched_rule": {
            "identifier": "apache-2.0_10.RULE",
            "license_expression": "apache-2.0",
            "licenses": [
              "apache-2.0"
            ],
            "is_license_text": false,
            "is_license_notice": false,
            "is_license_reference": true,
            "is_license_tag": false,
            "matcher": "2-aho",
            "rule_length": 5,
            "matched_length": 5,
            "match_coverage": 100.0,
            "rule_relevance": 27
          }
        },
        {
          "key": "apache-2.0",
          "score": 33.0,
          "name": "Apache License 2.0",
          "short_name": "Apache 2.0",
          "category": "Permissive",
          "is_exception": false,
          "owner": "Apache Software Foundation",
          "homepage_url": "http://www.apache.org/licenses/",
          "text_url": "http://www.apache.org/licenses/LICENSE-2.0",
          "reference_url": "https://enterprise.dejacode.com/urn/urn:dje:license:apache-2.0",
          "spdx_license_key": "Apache-2.0",
          "spdx_url": "https://spdx.org/licenses/Apache-2.0",
          "start_line": 17,
          "end_line": 17,
          "matched_rule": {
            "identifier": "pypi_apache_software_license.RULE",
            "license_expression": "apache-2.0",
            "licenses": [
              "apache-2.0"
            ],
            "is_license_text": false,
            "is_license_notice": false,
            "is_license_reference": false,
            "is_license_tag": true,
            "matcher": "2-aho",
            "rule_length": 6,
            "matched_length": 6,
            "match_coverage": 100.0,
            "rule_relevance": 33
          }
        }
      ],
      "license_expressions": [
        "apache-2.0",
        "apache-2.0"
      ],
      "holders": [],
      "copyrights": [],
      "authors": [
        {
          "value": "Certbot Project",
          "start_line": 6,
          "end_line": 9
        }
      ],
      "packages": [],
      "is_legal": false,
      "is_manifest": false,
      "is_readme": false,
      "is_top_level": true,
      "is_key_file": false,
      "files_count": 0,
      "dirs_count": 0,
      "size_count": 0,
      "scan_errors": []
    },
    {
      "path": "letsencrypt-0.7.0.tar.gz-extract/letsencrypt-0.7.0/README.rst",
      "type": "file",
      "name": "README.rst",
      "base_name": "README",
      "extension": ".rst",
      "size": 94,
      "date": "2016-05-27",
      "sha1": "fece7d4d5bc35896d05a70f9f455cf255b4ff0a4",
      "md5": "d2f3efbc393a889b65893e9ec0e3ba8e",
      "mime_type": "text/plain",
      "file_type": "ASCII text",
      "programming_language": null,
      "is_binary": false,
      "is_text": true,
      "is_archive": false,
      "is_media": false,
      "is_source": false,
      "is_script": false,
      "licenses": [],
      "license_expressions": [],
      "holders": [],
      "copyrights": [],
      "authors": [],
      "packages": [],
      "is_legal": false,
      "is_manifest": false,
      "is_readme": true,
      "is_top_level": true,
      "is_key_file": true,
      "files_count": 0,
      "dirs_count": 0,
      "size_count": 0,
      "scan_errors": []
    },
    {
      "path": "letsencrypt-0.7.0.tar.gz-extract/letsencrypt-0.7.0/setup.cfg",
      "type": "file",
      "name": "setup.cfg",
      "base_name": "setup",
      "extension": ".cfg",
      "size": 59,
      "date": "2016-05-27",
      "sha1": "68140cccea91d3e1c1e21a3416acd5551d0dea45",
      "md5": "d86758afb08a60bc589dc67bfea670b2",
      "mime_type": "text/plain",
      "file_type": "ASCII text",
      "programming_language": null,
      "is_binary": false,
      "is_text": true,
      "is_archive": false,
      "is_media": false,
      "is_source": false,
      "is_script": false,
      "licenses": [],
      "license_expressions": [],
      "holders": [],
      "copyrights": [],
      "authors": [],
      "packages": [],
      "is_legal": false,
      "is_manifest": true,
      "is_readme": false,
      "is_top_level": true,
      "is_key_file": true,
      "files_count": 0,
      "dirs_count": 0,
      "size_count": 0,
      "scan_errors": []
    },
    {
      "path": "letsencrypt-0.7.0.tar.gz-extract/letsencrypt-0.7.0/setup.py",
      "type": "file",
      "name": "setup.py",
      "base_name": "setup",
      "extension": ".py",
      "size": 1706,
      "date": "2016-05-27",
      "sha1": "91d1cb432d6dbeea8d390eb26ad978b9d9cfe326",
      "md5": "c36ddf57908ffffe1b2b3e0e95969f14",
      "mime_type": "text/x-python",
      "file_type": "Python script, ASCII text executable",
      "programming_language": "Python",
      "is_binary": false,
      "is_text": true,
      "is_archive": false,
      "is_media": false,
      "is_source": true,
      "is_script": true,
      "licenses": [
        {
          "key": "apache-2.0",
          "score": 27.0,
          "name": "Apache License 2.0",
          "short_name": "Apache 2.0",
          "category": "Permissive",
          "is_exception": false,
          "owner": "Apache Software Foundation",
          "homepage_url": "http://www.apache.org/licenses/",
          "text_url": "http://www.apache.org/licenses/LICENSE-2.0",
          "reference_url": "https://enterprise.dejacode.com/urn/urn:dje:license:apache-2.0",
          "spdx_license_key": "Apache-2.0",
          "spdx_url": "https://spdx.org/licenses/Apache-2.0",
          "start_line": 34,
          "end_line": 34,
          "matched_rule": {
            "identifier": "apache-2.0_10.RULE",
            "license_expression": "apache-2.0",
            "licenses": [
              "apache-2.0"
            ],
            "is_license_text": false,
            "is_license_notice": false,
            "is_license_reference": true,
            "is_license_tag": false,
            "matcher": "2-aho",
            "rule_length": 5,
            "matched_length": 5,
            "match_coverage": 100.0,
            "rule_relevance": 27
          }
        },
        {
          "key": "apache-2.0",
          "score": 33.0,
          "name": "Apache License 2.0",
          "short_name": "Apache 2.0",
          "category": "Permissive",
          "is_exception": false,
          "owner": "Apache Software Foundation",
          "homepage_url": "http://www.apache.org/licenses/",
          "text_url": "http://www.apache.org/licenses/LICENSE-2.0",
          "reference_url": "https://enterprise.dejacode.com/urn/urn:dje:license:apache-2.0",
          "spdx_license_key": "Apache-2.0",
          "spdx_url": "https://spdx.org/licenses/Apache-2.0",
          "start_line": 40,
          "end_line": 40,
          "matched_rule": {
            "identifier": "pypi_apache_software_license.RULE",
            "license_expression": "apache-2.0",
            "licenses": [
              "apache-2.0"
            ],
            "is_license_text": false,
            "is_license_notice": false,
            "is_license_reference": false,
            "is_license_tag": true,
            "matcher": "2-aho",
            "rule_length": 6,
            "matched_length": 6,
            "match_coverage": 100.0,
            "rule_relevance": 33
          }
        }
      ],
      "license_expressions": [
        "apache-2.0",
        "apache-2.0"
      ],
      "holders": [],
      "copyrights": [],
      "authors": [],
      "packages": [],
      "is_legal": false,
      "is_manifest": true,
      "is_readme": false,
      "is_top_level": true,
      "is_key_file": true,
      "files_count": 0,
      "dirs_count": 0,
      "size_count": 0,
      "scan_errors": []
    },
    {
      "path": "letsencrypt-0.7.0.tar.gz-extract/letsencrypt-0.7.0/letsencrypt",
      "type": "directory",
      "name": "letsencrypt",
      "base_name": "letsencrypt",
      "extension": "",
      "size": 0,
      "date": null,
      "sha1": null,
      "md5": null,
      "mime_type": null,
      "file_type": null,
      "programming_language": null,
      "is_binary": false,
      "is_text": false,
      "is_archive": false,
      "is_media": false,
      "is_source": false,
      "is_script": false,
      "licenses": [],
      "license_expressions": [],
      "holders": [],
      "copyrights": [],
      "authors": [],
      "packages": [],
      "is_legal": false,
      "is_manifest": false,
      "is_readme": false,
      "is_top_level": true,
      "is_key_file": false,
      "files_count": 1,
      "dirs_count": 0,
      "size_count": 100,
      "scan_errors": []
    },
    {
      "path": "letsencrypt-0.7.0.tar.gz-extract/letsencrypt-0.7.0/letsencrypt/__init__.py",
      "type": "file",
      "name": "__init__.py",
      "base_name": "__init__",
      "extension": ".py",
      "size": 100,
      "date": "2016-05-27",
      "sha1": "002c26aac49e1e58fb2eb972d959a4ba7ef6874b",
      "md5": "d674873215573e0dd9865c0ca9b6f28b",
      "mime_type": "text/plain",
      "file_type": "Python script, ASCII text executable",
      "programming_language": "Python",
      "is_binary": false,
      "is_text": true,
      "is_archive": false,
      "is_media": false,
      "is_source": true,
      "is_script": true,
      "licenses": [],
      "license_expressions": [],
      "holders": [],
      "copyrights": [],
      "authors": [],
      "packages": [],
      "is_legal": false,
      "is_manifest": false,
      "is_readme": false,
      "is_top_level": false,
      "is_key_file": false,
      "files_count": 0,
      "dirs_count": 0,
      "size_count": 0,
      "scan_errors": []
    },
    {
      "path": "letsencrypt-0.7.0.tar.gz-extract/letsencrypt-0.7.0/letsencrypt.egg-info",
      "type": "directory",
      "name": "letsencrypt.egg-info",
      "base_name": "letsencrypt.egg-info",
      "extension": "",
      "size": 0,
      "date": null,
      "sha1": null,
      "md5": null,
      "mime_type": null,
      "file_type": null,
      "programming_language": null,
      "is_binary": false,
      "is_text": false,
      "is_archive": false,
      "is_media": false,
      "is_source": false,
      "is_script": false,
      "licenses": [],
      "license_expressions": [],
      "holders": [],
      "copyrights": [],
      "authors": [],
      "packages": [],
      "is_legal": false,
      "is_manifest": false,
      "is_readme": false,
      "is_top_level": true,
      "is_key_file": false,
      "files_count": 6,
      "dirs_count": 0,
      "size_count": 1445,
      "scan_errors": []
    },
    {
      "path": "letsencrypt-0.7.0.tar.gz-extract/letsencrypt-0.7.0/letsencrypt.egg-info/dependency_links.txt",
      "type": "file",
      "name": "dependency_links.txt",
      "base_name": "dependency_links",
      "extension": ".txt",
      "size": 1,
      "date": "2016-05-27",
      "sha1": "adc83b19e793491b1c6ea0fd8b46cd9f32e592fc",
      "md5": "68b329da9893e34099c7d8ad5cb9c940",
      "mime_type": "application/octet-stream",
      "file_type": "very short file (no magic)",
      "programming_language": null,
      "is_binary": false,
      "is_text": true,
      "is_archive": false,
      "is_media": false,
      "is_source": false,
      "is_script": false,
      "licenses": [],
      "license_expressions": [],
      "holders": [],
      "copyrights": [],
      "authors": [],
      "packages": [],
      "is_legal": false,
      "is_manifest": false,
      "is_readme": false,
      "is_top_level": false,
      "is_key_file": false,
      "files_count": 0,
      "dirs_count": 0,
      "size_count": 0,
      "scan_errors": []
    },
    {
      "path": "letsencrypt-0.7.0.tar.gz-extract/letsencrypt-0.7.0/letsencrypt.egg-info/entry_points.txt",
      "type": "file",
      "name": "entry_points.txt",
      "base_name": "entry_points",
      "extension": ".txt",
      "size": 51,
      "date": "2016-05-27",
      "sha1": "ae2ba46f57835db78fb82da41c6da285f8ffadc7",
      "md5": "073b64faf98c564a06eea95c1e2a8d3d",
      "mime_type": "text/plain",
      "file_type": "ASCII text",
      "programming_language": null,
      "is_binary": false,
      "is_text": true,
      "is_archive": false,
      "is_media": false,
      "is_source": false,
      "is_script": false,
      "licenses": [],
      "license_expressions": [],
      "holders": [],
      "copyrights": [],
      "authors": [],
      "packages": [],
      "is_legal": false,
      "is_manifest": false,
      "is_readme": false,
      "is_top_level": false,
      "is_key_file": false,
      "files_count": 0,
      "dirs_count": 0,
      "size_count": 0,
      "scan_errors": []
    },
    {
      "path": "letsencrypt-0.7.0.tar.gz-extract/letsencrypt-0.7.0/letsencrypt.egg-info/PKG-INFO",
      "type": "file",
      "name": "PKG-INFO",
      "base_name": "PKG-INFO",
      "extension": "",
      "size": 1094,
      "date": "2016-05-27",
      "sha1": "049a7926c19876243bde3438eaf872bce00688ea",
      "md5": "ab37a1b85527b8bd13188b6363133db3",
      "mime_type": "text/plain",
      "file_type": "ASCII text",
      "programming_language": null,
      "is_binary": false,
      "is_text": true,
      "is_archive": false,
      "is_media": false,
      "is_source": false,
      "is_script": false,
      "licenses": [
        {
          "key": "apache-2.0",
          "score": 27.0,
          "name": "Apache License 2.0",
          "short_name": "Apache 2.0",
          "category": "Permissive",
          "is_exception": false,
          "owner": "Apache Software Foundation",
          "homepage_url": "http://www.apache.org/licenses/",
          "text_url": "http://www.apache.org/licenses/LICENSE-2.0",
          "reference_url": "https://enterprise.dejacode.com/urn/urn:dje:license:apache-2.0",
          "spdx_license_key": "Apache-2.0",
          "spdx_url": "https://spdx.org/licenses/Apache-2.0",
          "start_line": 8,
          "end_line": 8,
          "matched_rule": {
            "identifier": "apache-2.0_10.RULE",
            "license_expression": "apache-2.0",
            "licenses": [
              "apache-2.0"
            ],
            "is_license_text": false,
            "is_license_notice": false,
            "is_license_reference": true,
            "is_license_tag": false,
            "matcher": "2-aho",
            "rule_length": 5,
            "matched_length": 5,
            "match_coverage": 100.0,
            "rule_relevance": 27
          }
        },
        {
          "key": "apache-2.0",
          "score": 33.0,
          "name": "Apache License 2.0",
          "short_name": "Apache 2.0",
          "category": "Permissive",
          "is_exception": false,
          "owner": "Apache Software Foundation",
          "homepage_url": "http://www.apache.org/licenses/",
          "text_url": "http://www.apache.org/licenses/LICENSE-2.0",
          "reference_url": "https://enterprise.dejacode.com/urn/urn:dje:license:apache-2.0",
          "spdx_license_key": "Apache-2.0",
          "spdx_url": "https://spdx.org/licenses/Apache-2.0",
          "start_line": 17,
          "end_line": 17,
          "matched_rule": {
            "identifier": "pypi_apache_software_license.RULE",
            "license_expression": "apache-2.0",
            "licenses": [
              "apache-2.0"
            ],
            "is_license_text": false,
            "is_license_notice": false,
            "is_license_reference": false,
            "is_license_tag": true,
            "matcher": "2-aho",
            "rule_length": 6,
            "matched_length": 6,
            "match_coverage": 100.0,
            "rule_relevance": 33
          }
        }
      ],
      "license_expressions": [
        "apache-2.0",
        "apache-2.0"
      ],
      "holders": [],
      "copyrights": [],
      "authors": [
        {
          "value": "Certbot Project",
          "start_line": 6,
          "end_line": 9
        }
      ],
      "packages": [],
      "is_legal": false,
      "is_manifest": false,
      "is_readme": false,
      "is_top_level": false,
      "is_key_file": false,
      "files_count": 0,
      "dirs_count": 0,
      "size_count": 0,
      "scan_errors": []
    },
    {
      "path": "letsencrypt-0.7.0.tar.gz-extract/letsencrypt-0.7.0/letsencrypt.egg-info/requires.txt",
      "type": "file",
      "name": "requires.txt",
      "base_name": "requires",
      "extension": ".txt",
      "size": 8,
      "date": "2016-05-27",
      "sha1": "6a05361ffa0842e844a1426eeb2a41eb5778ddfe",
      "md5": "2e267c511f01906c389b6b19c69d11a8",
      "mime_type": "text/plain",
      "file_type": "ASCII text",
      "programming_language": null,
      "is_binary": false,
      "is_text": true,
      "is_archive": false,
      "is_media": false,
      "is_source": false,
      "is_script": false,
      "licenses": [],
      "license_expressions": [],
      "holders": [],
      "copyrights": [],
      "authors": [],
      "packages": [],
      "is_legal": false,
      "is_manifest": false,
      "is_readme": false,
      "is_top_level": false,
      "is_key_file": false,
      "files_count": 0,
      "dirs_count": 0,
      "size_count": 0,
      "scan_errors": []
    },
    {
      "path": "letsencrypt-0.7.0.tar.gz-extract/letsencrypt-0.7.0/letsencrypt.egg-info/SOURCES.txt",
      "type": "file",
      "name": "SOURCES.txt",
      "base_name": "SOURCES",
      "extension": ".txt",
      "size": 279,
      "date": "2016-05-27",
      "sha1": "8de6cf72873971edf85afafa312c8c777194179c",
      "md5": "57b4a59d60b9357953385468f9cc3ce4",
      "mime_type": "text/plain",
      "file_type": "ASCII text",
      "programming_language": null,
      "is_binary": false,
      "is_text": true,
      "is_archive": false,
      "is_media": false,
      "is_source": false,
      "is_script": false,
      "licenses": [],
      "license_expressions": [],
      "holders": [],
      "copyrights": [],
      "authors": [],
      "packages": [],
      "is_legal": false,
      "is_manifest": false,
      "is_readme": false,
      "is_top_level": false,
      "is_key_file": false,
      "files_count": 0,
      "dirs_count": 0,
      "size_count": 0,
      "scan_errors": []
    },
    {
      "path": "letsencrypt-0.7.0.tar.gz-extract/letsencrypt-0.7.0/letsencrypt.egg-info/top_level.txt",
      "type": "file",
      "name": "top_level.txt",
      "base_name": "top_level",
      "extension": ".txt",
      "size": 12,
      "date": "2016-05-27",
      "sha1": "843c404fc15c8fd5911501e3cb963d7353133ed2",
      "md5": "7c6eb702981a9c361b1df57d82c1b7f0",
      "mime_type": "text/plain",
      "file_type": "ASCII text",
      "programming_language": null,
      "is_binary": false,
      "is_text": true,
      "is_archive": false,
      "is_media": false,
      "is_source": false,
      "is_script": false,
      "licenses": [],
      "license_expressions": [],
      "holders": [],
      "copyrights": [],
      "authors": [],
      "packages": [],
      "is_legal": false,
      "is_manifest": false,
      "is_readme": false,
      "is_top_level": false,
      "is_key_file": false,
      "files_count": 0,
      "dirs_count": 0,
      "size_count": 0,
      "scan_errors": []
    }
  ]
}
