{
  "headers": [
    {
      "tool_name": "scancode-toolkit",
      "tool_version": "3.0.2.post488.5027c75",
      "options": {},
      "notice": "Generated with ScanCode and provided on an \"AS IS\" BASIS, WITHOUT WARRANTIES\nOR CONDITIONS OF ANY KIND, either express or implied. No content created from\nScanCode should be considered or used as legal advice. Consult an Attorney\nfor any legal advice.\nScanCode is a free software code scanning tool from nexB Inc. and others.\nVisit https://github.com/nexB/scancode-toolkit/ for support and download.",
      "start_timestamp": "2019-03-31T010343.003004",
      "end_timestamp": "2019-03-31T010343.755594",
      "message": null,
      "errors": [],
      "extra_data": {
        "files_count": 3
      }
    },
    {
      "tool_name": "scancode-toolkit",
      "tool_version": "3.0.2.post488.5027c75",
      "options": {},
      "notice": "Generated with ScanCode and provided on an \"AS IS\" BASIS, WITHOUT WARRANTIES\nOR CONDITIONS OF ANY KIND, either express or implied. No content created from\nScanCode should be considered or used as legal advice. Consult an Attorney\nfor any legal advice.\nScanCode is a free software code scanning tool from nexB Inc. and others.\nVisit https://github.com/nexB/scancode-toolkit/ for support and download.",
      "start_timestamp": "2019-03-31T153636.907672",
      "end_timestamp": "2019-03-31T153636.957254",
      "message": null,
      "errors": [],
      "extra_data": {
        "files_count": 3
      }
    }
  ],
  "license_clarity_score": {
    "score": 23,
    "has_declared_license_in_key_files": false,
    "file_level_license_and_copyright_coverage": 0.33,
    "has_consistent_key_and_file_level_licenses": false,
    "is_using_only_spdx_licenses": true,
    "has_full_text_for_all_licenses": false,
    "declared": false,
    "discovered": 0.33,
    "consistency": false,
    "spdx": true,
    "license_texts": false
  },
  "files": [
    {
      "path": "keycloak-jboss-adapter-core-4.5.0.Final-sources.jar-extract",
      "type": "directory",
      "name": "keycloak-jboss-adapter-core-4.5.0.Final-sources.jar-extract",
      "base_name": "keycloak-jboss-adapter-core-4.5.0.Final-sources.jar-extract",
      "extension": "",
      "size": 0,
      "date": null,
      "sha1": null,
      "md5": null,
      "mime_type": null,
      "file_type": null,
      "programming_language": null,
      "is_binary": false,
      "is_text": false,
      "is_archive": false,
      "is_media": false,
      "is_source": false,
      "is_script": false,
      "licenses": [],
      "license_expressions": [],
      "holders": [],
      "copyrights": [],
      "authors": [],
      "packages": [],
      "is_legal": false,
      "is_manifest": false,
      "is_readme": false,
      "is_top_level": true,
      "is_key_file": false,
      "files_count": 3,
      "dirs_count": 5,
      "size_count": 4884,
      "scan_errors": []
    },
    {
      "path": "keycloak-jboss-adapter-core-4.5.0.Final-sources.jar-extract/META-INF",
      "type": "directory",
      "name": "META-INF",
      "base_name": "META-INF",
      "extension": "",
      "size": 0,
      "date": null,
      "sha1": null,
      "md5": null,
      "mime_type": null,
      "file_type": null,
      "programming_language": null,
      "is_binary": false,
      "is_text": false,
      "is_archive": false,
      "is_media": false,
      "is_source": false,
      "is_script": false,
      "licenses": [],
      "license_expressions": [],
      "holders": [],
      "copyrights": [],
      "authors": [],
      "packages": [],
      "is_legal": false,
      "is_manifest": false,
      "is_readme": false,
      "is_top_level": true,
      "is_key_file": false,
      "files_count": 2,
      "dirs_count": 0,
      "size_count": 1020,
      "scan_errors": []
    },
    {
      "path": "keycloak-jboss-adapter-core-4.5.0.Final-sources.jar-extract/META-INF/INDEX.LIST",
      "type": "file",
      "name": "INDEX.LIST",
      "base_name": "INDEX",
      "extension": ".LIST",
      "size": 143,
      "date": "2018-09-26",
      "sha1": "bf176038b0e671026e072fd13c2615c16295d734",
      "md5": "67c77338808d16e6960af6c08e362215",
      "mime_type": "text/plain",
      "file_type": "ASCII text",
      "programming_language": null,
      "is_binary": false,
      "is_text": true,
      "is_archive": false,
      "is_media": false,
      "is_source": false,
      "is_script": false,
      "licenses": [],
      "license_expressions": [],
      "holders": [],
      "copyrights": [],
      "authors": [],
      "packages": [],
      "is_legal": false,
      "is_manifest": false,
      "is_readme": false,
      "is_top_level": false,
      "is_key_file": false,
      "files_count": 0,
      "dirs_count": 0,
      "size_count": 0,
      "scan_errors": []
    },
    {
      "path": "keycloak-jboss-adapter-core-4.5.0.Final-sources.jar-extract/META-INF/MANIFEST.MF",
      "type": "file",
      "name": "MANIFEST.MF",
      "base_name": "MANIFEST",
      "extension": ".MF",
      "size": 877,
      "date": "2018-09-26",
      "sha1": "dcdf4915279240722f6f44f42680afa83acaacda",
      "md5": "20ed3629cc8ddc057f6f1a436afa7558",
      "mime_type": "text/plain",
      "file_type": "ASCII text, with CRLF line terminators",
      "programming_language": null,
      "is_binary": false,
      "is_text": true,
      "is_archive": false,
      "is_media": false,
      "is_source": false,
      "is_script": false,
      "licenses": [],
      "license_expressions": [],
      "holders": [],
      "copyrights": [],
      "authors": [],
      "packages": [],
      "is_legal": false,
      "is_manifest": true,
      "is_readme": false,
      "is_top_level": false,
      "is_key_file": false,
      "files_count": 0,
      "dirs_count": 0,
      "size_count": 0,
      "scan_errors": []
    },
    {
      "path": "keycloak-jboss-adapter-core-4.5.0.Final-sources.jar-extract/org",
      "type": "directory",
      "name": "org",
      "base_name": "org",
      "extension": "",
      "size": 0,
      "date": null,
      "sha1": null,
      "md5": null,
      "mime_type": null,
      "file_type": null,
      "programming_language": null,
      "is_binary": false,
      "is_text": false,
      "is_archive": false,
      "is_media": false,
      "is_source": false,
      "is_script": false,
      "licenses": [],
      "license_expressions": [],
      "holders": [],
      "copyrights": [],
      "authors": [],
      "packages": [],
      "is_legal": false,
      "is_manifest": false,
      "is_readme": false,
      "is_top_level": true,
      "is_key_file": false,
      "files_count": 1,
      "dirs_count": 3,
      "size_count": 3864,
      "scan_errors": []
    },
    {
      "path": "keycloak-jboss-adapter-core-4.5.0.Final-sources.jar-extract/org/keycloak",
      "type": "directory",
      "name": "keycloak",
      "base_name": "keycloak",
      "extension": "",
      "size": 0,
      "date": null,
      "sha1": null,
      "md5": null,
      "mime_type": null,
      "file_type": null,
      "programming_language": null,
      "is_binary": false,
      "is_text": false,
      "is_archive": false,
      "is_media": false,
      "is_source": false,
      "is_script": false,
      "licenses": [],
      "license_expressions": [],
      "holders": [],
      "copyrights": [],
      "authors": [],
      "packages": [],
      "is_legal": false,
      "is_manifest": false,
      "is_readme": false,
      "is_top_level": false,
      "is_key_file": false,
      "files_count": 1,
      "dirs_count": 2,
      "size_count": 3864,
      "scan_errors": []
    },
    {
      "path": "keycloak-jboss-adapter-core-4.5.0.Final-sources.jar-extract/org/keycloak/adapters",
      "type": "directory",
      "name": "adapters",
      "base_name": "adapters",
      "extension": "",
      "size": 0,
      "date": null,
      "sha1": null,
      "md5": null,
      "mime_type": null,
      "file_type": null,
      "programming_language": null,
      "is_binary": false,
      "is_text": false,
      "is_archive": false,
      "is_media": false,
      "is_source": false,
      "is_script": false,
      "licenses": [],
      "license_expressions": [],
      "holders": [],
      "copyrights": [],
      "authors": [],
      "packages": [],
      "is_legal": false,
      "is_manifest": false,
      "is_readme": false,
      "is_top_level": false,
      "is_key_file": false,
      "files_count": 1,
      "dirs_count": 1,
      "size_count": 3864,
      "scan_errors": []
    },
    {
      "path": "keycloak-jboss-adapter-core-4.5.0.Final-sources.jar-extract/org/keycloak/adapters/jboss",
      "type": "directory",
      "name": "jboss",
      "base_name": "jboss",
      "extension": "",
      "size": 0,
      "date": null,
      "sha1": null,
      "md5": null,
      "mime_type": null,
      "file_type": null,
      "programming_language": null,
      "is_binary": false,
      "is_text": false,
      "is_archive": false,
      "is_media": false,
      "is_source": false,
      "is_script": false,
      "licenses": [],
      "license_expressions": [],
      "holders": [],
      "copyrights": [],
      "authors": [],
      "packages": [],
      "is_legal": false,
      "is_manifest": false,
      "is_readme": false,
      "is_top_level": false,
      "is_key_file": false,
      "files_count": 1,
      "dirs_count": 0,
      "size_count": 3864,
      "scan_errors": []
    },
    {
      "path": "keycloak-jboss-adapter-core-4.5.0.Final-sources.jar-extract/org/keycloak/adapters/jboss/KeycloakLoginModule.java",
      "type": "file",
      "name": "KeycloakLoginModule.java",
      "base_name": "KeycloakLoginModule",
      "extension": ".java",
      "size": 3864,
      "date": "2018-08-15",
      "sha1": "6f1199c18657dcd937b4f2192f2b4cc9f4575a07",
      "md5": "99bd6c4e5ec0459be512d6c31b4e7a23",
      "mime_type": "text/html",
      "file_type": "HTML document, ASCII text",
      "programming_language": "Java",
      "is_binary": false,
      "is_text": true,
      "is_archive": false,
      "is_media": false,
      "is_source": true,
      "is_script": false,
      "licenses": [
        {
          "key": "apache-2.0",
          "score": 100.0,
          "name": "Apache License 2.0",
          "short_name": "Apache 2.0",
          "category": "Permissive",
          "is_exception": false,
          "owner": "Apache Software Foundation",
          "homepage_url": "http://www.apache.org/licenses/",
          "text_url": "http://www.apache.org/licenses/LICENSE-2.0",
          "reference_url": "https://enterprise.dejacode.com/urn/urn:dje:license:apache-2.0",
          "spdx_license_key": "Apache-2.0",
          "spdx_url": "https://spdx.org/licenses/Apache-2.0",
          "start_line": 5,
          "end_line": 15,
          "matched_rule": {
            "identifier": "apache-2.0_7.RULE",
            "license_expression": "apache-2.0",
            "licenses": [
              "apache-2.0"
            ],
            "is_license_text": false,
            "is_license_notice": true,
            "is_license_reference": false,
            "is_license_tag": false,
            "matcher": "2-aho",
            "rule_length": 85,
            "matched_length": 85,
            "match_coverage": 100.0,
            "rule_relevance": 100
          }
        }
      ],
      "license_expressions": [
        "apache-2.0"
      ],
      "holders": [
        {
          "value": "Red Hat, Inc. and/or its affiliates and other contributors",
          "start_line": 2,
          "end_line": 3
        }
      ],
      "copyrights": [
        {
          "value": "Copyright 2016 Red Hat, Inc. and/or its affiliates and other contributors",
          "start_line": 2,
          "end_line": 3
        }
      ],
      "authors": [],
      "packages": [],
      "is_legal": false,
      "is_manifest": false,
      "is_readme": false,
      "is_top_level": false,
      "is_key_file": false,
      "files_count": 0,
      "dirs_count": 0,
      "size_count": 0,
      "scan_errors": []
    }
  ]
}
