{
  "headers": [
    {
      "tool_name": "scancode-toolkit",
      "tool_version": "3.0.2.post488.5027c75",
      "options": {},
      "notice": "Generated with ScanCode and provided on an \"AS IS\" BASIS, WITHOUT WARRANTIES\nOR CONDITIONS OF ANY KIND, either express or implied. No content created from\nScanCode should be considered or used as legal advice. Consult an Attorney\nfor any legal advice.\nScanCode is a free software code scanning tool from nexB Inc. and others.\nVisit https://github.com/nexB/scancode-toolkit/ for support and download.",
      "start_timestamp": "2019-03-31T011540.682158",
      "end_timestamp": "2019-03-31T011540.926888",
      "message": null,
      "errors": [],
      "extra_data": {
        "files_count": 3
      }
    },
    {
      "tool_name": "scancode-toolkit",
      "tool_version": "3.0.2.post488.5027c75",
      "options": {},
      "notice": "Generated with ScanCode and provided on an \"AS IS\" BASIS, WITHOUT WARRANTIES\nOR CONDITIONS OF ANY KIND, either express or implied. No content created from\nScanCode should be considered or used as legal advice. Consult an Attorney\nfor any legal advice.\nScanCode is a free software code scanning tool from nexB Inc. and others.\nVisit https://github.com/nexB/scancode-toolkit/ for support and download.",
      "start_timestamp": "2019-03-31T153656.916283",
      "end_timestamp": "2019-03-31T153656.966185",
      "message": null,
      "errors": [],
      "extra_data": {
        "files_count": 3
      }
    }
  ],
  "license_clarity_score": {
    "score": 0,
    "has_declared_license_in_key_files": false,
    "file_level_license_and_copyright_coverage": 0.0,
    "has_consistent_key_and_file_level_licenses": false,
    "is_using_only_spdx_licenses": false,
    "has_full_text_for_all_licenses": false,
    "declared": false,
    "discovered": 0.0,
    "consistency": false,
    "spdx": false,
    "license_texts": false
  },
  "files": [
    {
      "path": "swagger-hibernate-validations-1.5.21-sources.jar-extract",
      "type": "directory",
      "name": "swagger-hibernate-validations-1.5.21-sources.jar-extract",
      "base_name": "swagger-hibernate-validations-1.5.21-sources.jar-extract",
      "extension": "",
      "size": 0,
      "date": null,
      "sha1": null,
      "md5": null,
      "mime_type": null,
      "file_type": null,
      "programming_language": null,
      "is_binary": false,
      "is_text": false,
      "is_archive": false,
      "is_media": false,
      "is_source": false,
      "is_script": false,
      "licenses": [],
      "license_expressions": [],
      "holders": [],
      "copyrights": [],
      "authors": [],
      "packages": [],
      "is_legal": false,
      "is_manifest": false,
      "is_readme": false,
      "is_top_level": true,
      "is_key_file": false,
      "files_count": 3,
      "dirs_count": 5,
      "size_count": 3716,
      "scan_errors": []
    },
    {
      "path": "swagger-hibernate-validations-1.5.21-sources.jar-extract/io",
      "type": "directory",
      "name": "io",
      "base_name": "io",
      "extension": "",
      "size": 0,
      "date": null,
      "sha1": null,
      "md5": null,
      "mime_type": null,
      "file_type": null,
      "programming_language": null,
      "is_binary": false,
      "is_text": false,
      "is_archive": false,
      "is_media": false,
      "is_source": false,
      "is_script": false,
      "licenses": [],
      "license_expressions": [],
      "holders": [],
      "copyrights": [],
      "authors": [],
      "packages": [],
      "is_legal": false,
      "is_manifest": false,
      "is_readme": false,
      "is_top_level": true,
      "is_key_file": false,
      "files_count": 1,
      "dirs_count": 2,
      "size_count": 3550,
      "scan_errors": []
    },
    {
      "path": "swagger-hibernate-validations-1.5.21-sources.jar-extract/io/swagger",
      "type": "directory",
      "name": "swagger",
      "base_name": "swagger",
      "extension": "",
      "size": 0,
      "date": null,
      "sha1": null,
      "md5": null,
      "mime_type": null,
      "file_type": null,
      "programming_language": null,
      "is_binary": false,
      "is_text": false,
      "is_archive": false,
      "is_media": false,
      "is_source": false,
      "is_script": false,
      "licenses": [],
      "license_expressions": [],
      "holders": [],
      "copyrights": [],
      "authors": [],
      "packages": [],
      "is_legal": false,
      "is_manifest": false,
      "is_readme": false,
      "is_top_level": false,
      "is_key_file": false,
      "files_count": 1,
      "dirs_count": 1,
      "size_count": 3550,
      "scan_errors": []
    },
    {
      "path": "swagger-hibernate-validations-1.5.21-sources.jar-extract/io/swagger/validator",
      "type": "directory",
      "name": "validator",
      "base_name": "validator",
      "extension": "",
      "size": 0,
      "date": null,
      "sha1": null,
      "md5": null,
      "mime_type": null,
      "file_type": null,
      "programming_language": null,
      "is_binary": false,
      "is_text": false,
      "is_archive": false,
      "is_media": false,
      "is_source": false,
      "is_script": false,
      "licenses": [],
      "license_expressions": [],
      "holders": [],
      "copyrights": [],
      "authors": [],
      "packages": [],
      "is_legal": false,
      "is_manifest": false,
      "is_readme": false,
      "is_top_level": false,
      "is_key_file": false,
      "files_count": 1,
      "dirs_count": 0,
      "size_count": 3550,
      "scan_errors": []
    },
    {
      "path": "swagger-hibernate-validations-1.5.21-sources.jar-extract/io/swagger/validator/BeanValidator.java",
      "type": "file",
      "name": "BeanValidator.java",
      "base_name": "BeanValidator",
      "extension": ".java",
      "size": 3550,
      "date": "2018-04-11",
      "sha1": "d943250fd75976143aec38a20257665f359e381d",
      "md5": "22c0a8cc17edf767e8adb646167d998b",
      "mime_type": "text/plain",
      "file_type": "ASCII text",
      "programming_language": "Java",
      "is_binary": false,
      "is_text": true,
      "is_archive": false,
      "is_media": false,
      "is_source": true,
      "is_script": false,
      "licenses": [],
      "license_expressions": [],
      "holders": [],
      "copyrights": [],
      "authors": [],
      "packages": [],
      "is_legal": false,
      "is_manifest": false,
      "is_readme": false,
      "is_top_level": false,
      "is_key_file": false,
      "files_count": 0,
      "dirs_count": 0,
      "size_count": 0,
      "scan_errors": []
    },
    {
      "path": "swagger-hibernate-validations-1.5.21-sources.jar-extract/META-INF",
      "type": "directory",
      "name": "META-INF",
      "base_name": "META-INF",
      "extension": "",
      "size": 0,
      "date": null,
      "sha1": null,
      "md5": null,
      "mime_type": null,
      "file_type": null,
      "programming_language": null,
      "is_binary": false,
      "is_text": false,
      "is_archive": false,
      "is_media": false,
      "is_source": false,
      "is_script": false,
      "licenses": [],
      "license_expressions": [],
      "holders": [],
      "copyrights": [],
      "authors": [],
      "packages": [],
      "is_legal": false,
      "is_manifest": false,
      "is_readme": false,
      "is_top_level": true,
      "is_key_file": false,
      "files_count": 2,
      "dirs_count": 1,
      "size_count": 166,
      "scan_errors": []
    },
    {
      "path": "swagger-hibernate-validations-1.5.21-sources.jar-extract/META-INF/MANIFEST.MF",
      "type": "file",
      "name": "MANIFEST.MF",
      "base_name": "MANIFEST",
      "extension": ".MF",
      "size": 132,
      "date": "2018-08-09",
      "sha1": "628391222d5c61ffc00a7c422047716d18abfe70",
      "md5": "ee11984bd03f287ec3656bb31f77c4a4",
      "mime_type": "text/plain",
      "file_type": "ASCII text, with CRLF line terminators",
      "programming_language": null,
      "is_binary": false,
      "is_text": true,
      "is_archive": false,
      "is_media": false,
      "is_source": false,
      "is_script": false,
      "licenses": [],
      "license_expressions": [],
      "holders": [],
      "copyrights": [],
      "authors": [],
      "packages": [],
      "is_legal": false,
      "is_manifest": true,
      "is_readme": false,
      "is_top_level": false,
      "is_key_file": false,
      "files_count": 0,
      "dirs_count": 0,
      "size_count": 0,
      "scan_errors": []
    },
    {
      "path": "swagger-hibernate-validations-1.5.21-sources.jar-extract/META-INF/services",
      "type": "directory",
      "name": "services",
      "base_name": "services",
      "extension": "",
      "size": 0,
      "date": null,
      "sha1": null,
      "md5": null,
      "mime_type": null,
      "file_type": null,
      "programming_language": null,
      "is_binary": false,
      "is_text": false,
      "is_archive": false,
      "is_media": false,
      "is_source": false,
      "is_script": false,
      "licenses": [],
      "license_expressions": [],
      "holders": [],
      "copyrights": [],
      "authors": [],
      "packages": [],
      "is_legal": false,
      "is_manifest": false,
      "is_readme": false,
      "is_top_level": false,
      "is_key_file": false,
      "files_count": 1,
      "dirs_count": 0,
      "size_count": 34,
      "scan_errors": []
    },
    {
      "path": "swagger-hibernate-validations-1.5.21-sources.jar-extract/META-INF/services/io.swagger.converter.ModelConverter",
      "type": "file",
      "name": "io.swagger.converter.ModelConverter",
      "base_name": "io.swagger.converter",
      "extension": ".ModelConverter",
      "size": 34,
      "date": "2018-04-11",
      "sha1": "0f876b07ecfa125e0001639b42952c1db2cff5ef",
      "md5": "f31e66af2f7f6bf93b39d108500efd5f",
      "mime_type": "text/plain",
      "file_type": "ASCII text, with no line terminators",
      "programming_language": null,
      "is_binary": false,
      "is_text": true,
      "is_archive": false,
      "is_media": false,
      "is_source": false,
      "is_script": false,
      "licenses": [],
      "license_expressions": [],
      "holders": [],
      "copyrights": [],
      "authors": [],
      "packages": [],
      "is_legal": false,
      "is_manifest": false,
      "is_readme": false,
      "is_top_level": false,
      "is_key_file": false,
      "files_count": 0,
      "dirs_count": 0,
      "size_count": 0,
      "scan_errors": []
    }
  ]
}
